thrash_protect.py
thrash_protect-0.15.8.dist-info/licenses/AUTHORS
thrash_protect-0.15.8.dist-info/licenses/LICENSE
thrash_protect-0.15.8.dist-info/METADATA
thrash_protect-0.15.8.dist-info/WHEEL
thrash_protect-0.15.8.dist-info/entry_points.txt
thrash_protect-0.15.8.dist-info/top_level.txt
thrash_protect-0.15.8.dist-info/RECORD
