Metadata-Version: 2.4
Name: thrash-protect
Version: 0.15.8
Summary: Simple-Stupid user-space program doing 'kill -STOP' and 'kill -CONT' to protect from thrashing
Author-email: Tobias Brox <tobias@redpill-linpro.com>
License: GPL-3.0-or-later
Project-URL: Homepage, https://github.com/tobixen/thrash-protect
Project-URL: Repository, https://github.com/tobixen/thrash-protect
Project-URL: Issues, https://github.com/tobixen/thrash-protect/issues
Keywords: thrashing,swap,memory,linux,system-administration
Classifier: Development Status :: 4 - Beta
Classifier: Environment :: No Input/Output (Daemon)
Classifier: Intended Audience :: System Administrators
Classifier: License :: OSI Approved :: GNU General Public License v3 or later (GPLv3+)
Classifier: Operating System :: POSIX :: Linux
Classifier: Programming Language :: Python :: 3
Classifier: Programming Language :: Python :: 3.9
Classifier: Programming Language :: Python :: 3.10
Classifier: Programming Language :: Python :: 3.11
Classifier: Programming Language :: Python :: 3.12
Classifier: Programming Language :: Python :: 3.13
Classifier: Topic :: System :: Monitoring
Classifier: Topic :: System :: Systems Administration
Classifier: Topic :: Utilities
Requires-Python: >=3.9
License-File: LICENSE
License-File: AUTHORS
Provides-Extra: dev
Requires-Dist: pytest>=7.0; extra == "dev"
Requires-Dist: pytest-cov>=4.0; extra == "dev"
Requires-Dist: ruff>=0.1.0; extra == "dev"
Requires-Dist: pre-commit>=3.0; extra == "dev"
Dynamic: license-file
